hr_selection_function/__init__.py
hr_selection_function/config.py
hr_selection_function/data.py
hr_selection_function/gaia.py
hr_selection_function/math.py
hr_selection_function/models.py
hr_selection_function-1.0.1.dist-info/METADATA
hr_selection_function-1.0.1.dist-info/WHEEL
hr_selection_function-1.0.1.dist-info/licenses/LICENSE
hr_selection_function-1.0.1.dist-info/RECORD
