Metadata-Version: 2.4
Name: hr_selection_function
Version: 1.0.1
Summary: Models and source code for the Hunt et al. 2025/2026 paper 'The selection function of the Gaia DR3 open cluster census', which establishes the selection function for the Hunt & Reffert 2024 open cluster catalogue.
Author-email: emilyhunt <emily.hunt.physics@gmail.com>
License-File: LICENSE
Requires-Python: >=3.9
Requires-Dist: astropy-healpix>=1.0.0
Requires-Dist: astropy>=5.0.0
Requires-Dist: astroquery>=0.4.0
Requires-Dist: healpy>=1.13.0
Requires-Dist: numba>=0.50.0
Requires-Dist: pandas>=1.0.0
Requires-Dist: pyarrow
Requires-Dist: tqdm>=3.0.0
Requires-Dist: xgboost>=3.0.0
Provides-Extra: dev
Requires-Dist: pytest; extra == 'dev'
Requires-Dist: ruff; extra == 'dev'
Provides-Extra: notebooks
Requires-Dist: dustmaps; extra == 'notebooks'
Requires-Dist: gala; extra == 'notebooks'
Requires-Dist: notebook>=6.0.0; extra == 'notebooks'
Requires-Dist: ocelot==0.4.5; extra == 'notebooks'
